[
  {
    "thumb": "red1.png",
    "image": "red1.png",
    "isVip": false
  },
  {
    "thumb": "red2.png",
    "image": "red2.png",
    "isVip": true
  },
  {
    "thumb": "red3.png",
    "image": "red3.png",
    "isVip": true
  },
  {
    "thumb": "red4.png",
    "image": "red4.png",
    "isVip": true
  },
  {
    "thumb": "red5.png",
    "image": "red5.png",
    "isVip": true
  },
  {
    "thumb": "red6.png",
    "image": "red6.png",
    "isVip": true
  },
  {
    "thumb": "red7.png",
    "image": "red7.png",
    "isVip": true
  },
  {
    "thumb": "red8.png",
    "image": "red8.png",
    "isVip": false
  },
  {
    "thumb": "red9.png",
    "image": "red9.png",
    "isVip": true
  },
  {
    "thumb": "red10.png",
    "image": "red10.png",
    "isVip": true
  },
  {
    "thumb": "red11.png",
    "image": "red11.png",
    "isVip": true
  },
  {
    "thumb": "red12.png",
    "image": "red12.png",
    "isVip": false
  },
  {
    "thumb": "red13.png",
    "image": "red13.png",
    "isVip": true
  },
  {
    "thumb": "red14.png",
    "image": "red14.png",
    "isVip": false
  },
  {
    "thumb": "red15.png",
    "image": "red15.png",
    "isVip": true
  },
  {
    "thumb": "red16.png",
    "image": "red16.png",
    "isVip": true
  },
  {
    "thumb": "red17.png",
    "image": "red17.png",
    "isVip": true
  },
  {
    "thumb": "red18.png",
    "image": "red18.png",
    "isVip": true
  },
  {
    "thumb": "red19.png",
    "image": "red19.png",
    "isVip": true
  },
  {
    "thumb": "red20.png",
    "image": "red20.png",
    "isVip": true
  },
  {
    "thumb": "red21.png",
    "image": "red21.png",
    "isVip": true
  },
  {
    "thumb": "red22.png",
    "image": "red22.png",
    "isVip": true
  },
  {
    "thumb": "red23.png",
    "image": "red23.png",
    "isVip": false
  },
  {
    "thumb": "red24.png",
    "image": "red24.png",
    "isVip": true
  },
  {
    "thumb": "red25.png",
    "image": "red25.png",
    "isVip": true
  },
  {
    "thumb": "red26.png",
    "image": "red26.png",
    "isVip": false
  },
  {
    "thumb": "red27.png",
    "image": "red27.png",
    "isVip": true
  },
  {
    "thumb": "red28.png",
    "image": "red28.png",
    "isVip": true
  },
  {
    "thumb": "red29.png",
    "image": "red29.png",
    "isVip": true
  },
  {
    "thumb": "red30.png",
    "image": "red30.png",
    "isVip": true
  }

]
